foundry_map_tool.py
foundry_map_tool-0.2.0.dist-info/METADATA
foundry_map_tool-0.2.0.dist-info/WHEEL
foundry_map_tool-0.2.0.dist-info/top_level.txt
foundry_map_tool-0.2.0.dist-info/RECORD
