Metadata-Version: 2.1
Name: foundry-map-tool
Version: 0.2.0
Summary: A tool to adjust the scale of maps in JSON files for Foundry VTT.
Author: Rory Burke
Author-email: RoryABurke+DAMapTool@gmail.com
Requires-Python: >=3.13
